npustat/__init__.py
npustat/__main__.py
npustat/ascend_dmi.py
npustat/cli.py
npustat/core.py
npustat/npu_smi.py
npustat-0.0.2.dist-info/LICENSE
npustat-0.0.2.dist-info/METADATA
npustat-0.0.2.dist-info/WHEEL
npustat-0.0.2.dist-info/entry_points.txt
npustat-0.0.2.dist-info/top_level.txt
npustat-0.0.2.dist-info/RECORD
