Metadata-Version: 2.1
Name: npustat
Version: 0.0.2
Summary: An utility to monitor Huawei Atlas status and usage
Home-page: https://github.com/wmc1992/npustat
Author: wmc1992
Author-email: m18810541081@163.com
License: MIT
Keywords: atlas npu monitoring npustat
Platform: UNKNOWN
Classifier: License :: OSI Approved :: MIT License
Classifier: Operating System :: POSIX :: Linux
Classifier: Programming Language :: Python :: 3
Classifier: Topic :: System :: Monitoring
Requires-Python: >=3.6
License-File: LICENSE
Requires-Dist: six (>=1.7)
Requires-Dist: blessed (>=1.17.1)
